awscostexport/__init__.py
awscostexport/cli.py
awscostexport/exporter.py
awscostexport-1.3.2.dist-info/licenses/LICENSE
awscostexport-1.3.2.dist-info/METADATA
awscostexport-1.3.2.dist-info/WHEEL
awscostexport-1.3.2.dist-info/entry_points.txt
awscostexport-1.3.2.dist-info/top_level.txt
awscostexport-1.3.2.dist-info/RECORD
