Metadata-Version: 2.4
Name: awscostexport
Version: 1.3.2
Summary: Export comprehensive AWS cost data for analysis and optimization
Home-page: https://github.com/trilogy-group/aws-cost-extractor
Author: David Schwartz
Author-email: david.schwartz@devfactory.com
Project-URL: Bug Reports, https://github.com/trilogy-group/aws-cost-extractor/issues
Project-URL: Source, https://github.com/trilogy-group/aws-cost-extractor
Classifier: Development Status :: 5 - Production/Stable
Classifier: Intended Audience :: Developers
Classifier: Intended Audience :: System Administrators
Classifier: Topic :: Office/Business :: Financial
Classifier: Topic :: System :: Systems Administration
Classifier: License :: OSI Approved :: MIT License
Classifier: Programming Language :: Python :: 3
Classifier: Programming Language :: Python :: 3.7
Classifier: Programming Language :: Python :: 3.8
Classifier: Programming Language :: Python :: 3.9
Classifier: Programming Language :: Python :: 3.10
Classifier: Programming Language :: Python :: 3.11
Classifier: Operating System :: OS Independent
Requires-Python: >=3.7
License-File: LICENSE
Requires-Dist: boto3>=1.26.0
Requires-Dist: click>=8.0.0
Requires-Dist: PyYAML>=6.0
Dynamic: author
Dynamic: author-email
Dynamic: classifier
Dynamic: description
Dynamic: description-content-type
Dynamic: home-page
Dynamic: license-file
Dynamic: project-url
Dynamic: requires-dist
Dynamic: requires-python
Dynamic: summary
